MANIFEST.in
README.md
build_cffi.py
setup.py
libimagequant2/__init__.py
libimagequant2.egg-info/PKG-INFO
libimagequant2.egg-info/SOURCES.txt
libimagequant2.egg-info/dependency_links.txt
libimagequant2.egg-info/requires.txt
libimagequant2.egg-info/top_level.txt
libimagequant_c/.gitignore
libimagequant_c/.travis.yml
libimagequant_c/CHANGELOG
libimagequant_c/CMakeLists.txt
libimagequant_c/CODE_OF_CONDUCT.md
libimagequant_c/CONTRIBUTING.md
libimagequant_c/COPYRIGHT
libimagequant_c/Cargo.toml
libimagequant_c/Makefile
libimagequant_c/README.md
libimagequant_c/blur.c
libimagequant_c/blur.h
libimagequant_c/configure
libimagequant_c/example.c
libimagequant_c/imagequant.pc.in
libimagequant_c/kmeans.c
libimagequant_c/kmeans.h
libimagequant_c/libimagequant.c
libimagequant_c/libimagequant.cs
libimagequant_c/libimagequant.h
libimagequant_c/mediancut.c
libimagequant_c/mediancut.h
libimagequant_c/mempool.c
libimagequant_c/mempool.h
libimagequant_c/nearest.c
libimagequant_c/nearest.h
libimagequant_c/pam.c
libimagequant_c/pam.h
libimagequant_c/pom.xml
libimagequant_c/libimagequant-ios.xcodeproj/project.pbxproj
libimagequant_c/libimagequant-mac.xcodeproj/project.pbxproj
libimagequant_c/org/pngquant/Image.java
libimagequant_c/org/pngquant/LiqObject.java
libimagequant_c/org/pngquant/PngQuant.c
libimagequant_c/org/pngquant/PngQuant.java
libimagequant_c/org/pngquant/PngQuantException.java
libimagequant_c/org/pngquant/Result.java
libimagequant_c/rust-api/.gitignore
libimagequant_c/rust-api/COPYRIGHT
libimagequant_c/rust-api/Cargo.toml
libimagequant_c/rust-api/README.md
libimagequant_c/rust-api/examples/basic.rs
libimagequant_c/rust-api/src/lib.rs
libimagequant_c/rust-sys/build.rs
libimagequant_c/rust-sys/libimagequant.rs