Metadata-Version: 1.2
Name: libimagequant2
Version: 2.14.4
Summary: Unofficial Python bindings for libimagequant
Home-page: https://github.com/RoadrunnerWMC/libimagequant-python
Author: RoadrunnerWMC, Kornel Lesiński
Author-email: roadrunnerwmc@gmail.com
License: UNKNOWN
Platform: UNKNOWN
Classifier: Programming Language :: C
Classifier: Programming Language :: Python :: 2.7
Classifier: Programming Language :: Python :: 3.5
Classifier: Programming Language :: Python :: 3.6
Classifier: Programming Language :: Python :: 3.7
Classifier: Programming Language :: Python :: 3.8
Classifier: Programming Language :: Python :: 3.9
Classifier: Programming Language :: Python :: Implementation :: PyPy
Classifier: Topic :: Multimedia :: Graphics
Classifier: License :: OSI Approved :: GNU General Public License v3 or later (GPLv3+)
Requires-Python: >=2.7
